[{"line":1,"elements":[{"line":3,"name":"","description":"","type":"background","keyword":"Background","steps":[{"result":{"duration":1503500,"status":"passed"},"line":4,"name":"Set the entries from the data base","match":{"location":"StepDefinition.login_Step.getEntries()"},"keyword":"Given "},{"result":{"status":"passed"},"line":5,"name":"User enter launches browser from config file","match":{"location":"StepDefinition.login_Step.launchBrowser()"},"keyword":"When "},{"result":{"status":"passed"},"line":6,"name":"user get the URL","match":{"location":"StepDefinition.login_Step.getUrl()"},"keyword":"And "}]},{"start_timestamp":"2023-12-17T13:16:13.999Z","line":9,"name":"Admin Login page","description":"","id":"login-page-feature;admin-login-page","after":[{"result":{"status":"passed"},"match":{"location":"StepDefinition.Hooks.clearData()"}}],"type":"scenario","keyword":"Scenario","steps":[{"result":{"status":"passed"},"line":10,"name":"User is on Net bank login page","match":{"location":"StepDefinition.login_Step.user_is_on_net_bank_login_page()"},"keyword":"Given "},{"result":{"duration":1000600,"status":"passed"},"line":11,"name":"User enter username \"Admin\" and password 12345","match":{"arguments":[{"val":"\"Admin\"","offset":20},{"val":"12345","offset":41}],"location":"StepDefinition.login_Step.user_enter_user_name_and_password(java.lang.String,java.lang.String)"},"keyword":"When "},{"result":{"status":"passed"},"line":12,"name":"User uccessfully navigate to the home page","match":{"location":"StepDefinition.login_Step.user_uccessfully_navigate_to_the_home_page()"},"keyword":"Then "}],"tags":[{"name":"@smoke"}]},{"line":3,"name":"","description":"","type":"background","keyword":"Background","steps":[{"result":{"status":"passed"},"line":4,"name":"Set the entries from the data base","match":{"location":"StepDefinition.login_Step.getEntries()"},"keyword":"Given "},{"result":{"status":"passed"},"line":5,"name":"User enter launches browser from config file","match":{"location":"StepDefinition.login_Step.launchBrowser()"},"keyword":"When "},{"result":{"status":"passed"},"line":6,"name":"user get the URL","match":{"location":"StepDefinition.login_Step.getUrl()"},"keyword":"And "}]},{"start_timestamp":"2023-12-17T13:16:14.017Z","line":24,"name":"Multiuser login","description":"","id":"login-page-feature;multiuser-login;;2","after":[{"result":{"status":"passed"},"match":{"location":"StepDefinition.Hooks.clearData()"}}],"type":"scenario","keyword":"Scenario Outline","steps":[{"result":{"duration":999900,"status":"passed"},"line":18,"name":"User is on Net bank login page","match":{"location":"StepDefinition.login_Step.user_is_on_net_bank_login_page()"},"keyword":"Given "},{"result":{"status":"passed"},"line":19,"name":"User enter username \"NetbankUser\" and password 123","match":{"arguments":[{"val":"\"NetbankUser\"","offset":20},{"val":"123","offset":47}],"location":"StepDefinition.login_Step.user_enter_user_name_and_password(java.lang.String,java.lang.String)"},"keyword":"When "},{"result":{"status":"passed"},"line":20,"name":"User uccessfully navigate to the home page","match":{"location":"StepDefinition.login_Step.user_uccessfully_navigate_to_the_home_page()"},"keyword":"Then "}],"tags":[{"name":"@Regration"}]},{"line":3,"name":"","description":"","type":"background","keyword":"Background","steps":[{"result":{"status":"passed"},"line":4,"name":"Set the entries from the data base","match":{"location":"StepDefinition.login_Step.getEntries()"},"keyword":"Given "},{"result":{"duration":1001100,"status":"passed"},"line":5,"name":"User enter launches browser from config file","match":{"location":"StepDefinition.login_Step.launchBrowser()"},"keyword":"When "},{"result":{"status":"passed"},"line":6,"name":"user get the URL","match":{"location":"StepDefinition.login_Step.getUrl()"},"keyword":"And "}]},{"start_timestamp":"2023-12-17T13:16:14.025Z","line":25,"name":"Multiuser login","description":"","id":"login-page-feature;multiuser-login;;3","after":[{"result":{"status":"passed"},"match":{"location":"StepDefinition.Hooks.clearData()"}}],"type":"scenario","keyword":"Scenario Outline","steps":[{"result":{"duration":1001100,"status":"passed"},"line":18,"name":"User is on Net bank login page","match":{"location":"StepDefinition.login_Step.user_is_on_net_bank_login_page()"},"keyword":"Given "},{"result":{"status":"passed"},"line":19,"name":"User enter username \"CreditcardUser\" and password 199","match":{"arguments":[{"val":"\"CreditcardUser\"","offset":20},{"val":"199","offset":50}],"location":"StepDefinition.login_Step.user_enter_user_name_and_password(java.lang.String,java.lang.String)"},"keyword":"When "},{"result":{"status":"passed"},"line":20,"name":"User uccessfully navigate to the home page","match":{"location":"StepDefinition.login_Step.user_uccessfully_navigate_to_the_home_page()"},"keyword":"Then "}],"tags":[{"name":"@Regration"}]},{"line":3,"name":"","description":"","type":"background","keyword":"Background","steps":[{"result":{"status":"passed"},"line":4,"name":"Set the entries from the data base","match":{"location":"StepDefinition.login_Step.getEntries()"},"keyword":"Given "},{"result":{"status":"passed"},"line":5,"name":"User enter launches browser from config file","match":{"location":"StepDefinition.login_Step.launchBrowser()"},"keyword":"When "},{"result":{"status":"passed"},"line":6,"name":"user get the URL","match":{"location":"StepDefinition.login_Step.getUrl()"},"keyword":"And "}]},{"start_timestamp":"2023-12-17T13:16:14.034Z","line":26,"name":"Multiuser login","description":"","id":"login-page-feature;multiuser-login;;4","after":[{"result":{"status":"passed"},"match":{"location":"StepDefinition.Hooks.clearData()"}}],"type":"scenario","keyword":"Scenario Outline","steps":[{"result":{"status":"passed"},"line":18,"name":"User is on Net bank login page","match":{"location":"StepDefinition.login_Step.user_is_on_net_bank_login_page()"},"keyword":"Given "},{"result":{"status":"passed"},"line":19,"name":"User enter username \"DebitcardUser\" and password 100","match":{"arguments":[{"val":"\"DebitcardUser\"","offset":20},{"val":"100","offset":49}],"location":"StepDefinition.login_Step.user_enter_user_name_and_password(java.lang.String,java.lang.String)"},"keyword":"When "},{"result":{"status":"passed"},"line":20,"name":"User uccessfully navigate to the home page","match":{"location":"StepDefinition.login_Step.user_uccessfully_navigate_to_the_home_page()"},"keyword":"Then "}],"tags":[{"name":"@Regration"}]},{"line":3,"name":"","description":"","type":"background","keyword":"Background","steps":[{"result":{"status":"passed"},"line":4,"name":"Set the entries from the data base","match":{"location":"StepDefinition.login_Step.getEntries()"},"keyword":"Given "},{"result":{"status":"passed"},"line":5,"name":"User enter launches browser from config file","match":{"location":"StepDefinition.login_Step.launchBrowser()"},"keyword":"When "},{"result":{"status":"passed"},"line":6,"name":"user get the URL","match":{"location":"StepDefinition.login_Step.getUrl()"},"keyword":"And "}]},{"start_timestamp":"2023-12-17T13:16:14.041Z","line":30,"name":"Userregistration signup page","description":"","id":"login-page-feature;userregistration-signup-page","after":[{"result":{"status":"passed"},"match":{"location":"StepDefinition.Hooks.clearData()"}}],"type":"scenario","keyword":"Scenario","steps":[{"result":{"status":"passed"},"line":31,"name":"User is on registration page","match":{"location":"StepDefinition.login_Step.user_is_on_registration_page()"},"keyword":"Given "},{"result":{"duration":3021700,"status":"passed"},"line":32,"name":"User enter details in regisyration page","match":{"location":"StepDefinition.login_Step.user_enter_details_in_regisyration_page(java.util.List<java.lang.Object>)"},"rows":[{"cells":["anj"]},{"cells":["martha"]},{"cells":["man"]},{"cells":["anj@gmail.com"]},{"cells":["1.009"]},{"cells":["504502"]}],"keyword":"When "},{"result":{"status":"passed"},"line":40,"name":"User successfully registered","match":{"location":"StepDefinition.login_Step.user_successfully_registered()"},"keyword":"Then "}],"tags":[{"name":"@Unit"},{"name":"@Regration"}]}],"name":"Login page Feature","description":"","id":"login-page-feature","keyword":"Feature","uri":"file:src/test/java/feature/login.feature","tags":[]},{"line":1,"elements":[{"line":3,"name":"","description":"","type":"background","keyword":"Background","steps":[{"result":{"status":"passed"},"line":5,"name":"User enter launches browser from config file","match":{"location":"StepDefinition.login_Step.launchBrowser()"},"keyword":"When "},{"result":{"duration":990300,"status":"passed"},"line":6,"name":"user get the URL","match":{"location":"StepDefinition.login_Step.getUrl()"},"keyword":"And "}]},{"start_timestamp":"2023-12-17T13:16:14.053Z","before":[{"result":{"status":"passed"},"match":{"location":"StepDefinition.Hooks.netBanking()"}}],"line":20,"name":"Multiuser login","description":"","id":"login-page-hooks-feature;multiuser-login;;2","after":[{"result":{"status":"passed"},"match":{"location":"StepDefinition.Hooks.clearData()"}}],"type":"scenario","keyword":"Scenario Outline","steps":[{"result":{"status":"passed"},"line":14,"name":"User is on Net bank login page","match":{"location":"StepDefinition.login_Step.user_is_on_net_bank_login_page()"},"keyword":"Given "},{"result":{"status":"passed"},"line":15,"name":"User enter username \"NetbankUser\" and password 123","match":{"arguments":[{"val":"\"NetbankUser\"","offset":20},{"val":"123","offset":47}],"location":"StepDefinition.login_Step.user_enter_user_name_and_password(java.lang.String,java.lang.String)"},"keyword":"When "},{"result":{"status":"passed"},"line":16,"name":"User uccessfully navigate to the home page","match":{"location":"StepDefinition.login_Step.user_uccessfully_navigate_to_the_home_page()"},"keyword":"Then "}],"tags":[{"name":"@smoke"},{"name":"@Regration"},{"name":"@Netbank"}]},{"line":3,"name":"","description":"","type":"background","keyword":"Background","steps":[{"result":{"status":"passed"},"line":5,"name":"User enter launches browser from config file","match":{"location":"StepDefinition.login_Step.launchBrowser()"},"keyword":"When "},{"result":{"duration":1000500,"status":"passed"},"line":6,"name":"user get the URL","match":{"location":"StepDefinition.login_Step.getUrl()"},"keyword":"And "}]},{"start_timestamp":"2023-12-17T13:16:14.063Z","before":[{"result":{"status":"passed"},"match":{"location":"StepDefinition.Hooks.netBanking()"}}],"line":21,"name":"Multiuser login","description":"","id":"login-page-hooks-feature;multiuser-login;;3","after":[{"result":{"status":"passed"},"match":{"location":"StepDefinition.Hooks.clearData()"}}],"type":"scenario","keyword":"Scenario Outline","steps":[{"result":{"status":"passed"},"line":14,"name":"User is on Net bank login page","match":{"location":"StepDefinition.login_Step.user_is_on_net_bank_login_page()"},"keyword":"Given "},{"result":{"duration":502900,"status":"passed"},"line":15,"name":"User enter username \"CreditcardUser\" and password 199","match":{"arguments":[{"val":"\"CreditcardUser\"","offset":20},{"val":"199","offset":50}],"location":"StepDefinition.login_Step.user_enter_user_name_and_password(java.lang.String,java.lang.String)"},"keyword":"When "},{"result":{"status":"passed"},"line":16,"name":"User uccessfully navigate to the home page","match":{"location":"StepDefinition.login_Step.user_uccessfully_navigate_to_the_home_page()"},"keyword":"Then "}],"tags":[{"name":"@smoke"},{"name":"@Regration"},{"name":"@Netbank"}]},{"line":3,"name":"","description":"","type":"background","keyword":"Background","steps":[{"result":{"status":"passed"},"line":5,"name":"User enter launches browser from config file","match":{"location":"StepDefinition.login_Step.launchBrowser()"},"keyword":"When "},{"result":{"status":"passed"},"line":6,"name":"user get the URL","match":{"location":"StepDefinition.login_Step.getUrl()"},"keyword":"And "}]},{"start_timestamp":"2023-12-17T13:16:14.067Z","before":[{"result":{"status":"passed"},"match":{"location":"StepDefinition.Hooks.netBanking()"}}],"line":22,"name":"Multiuser login","description":"","id":"login-page-hooks-feature;multiuser-login;;4","after":[{"result":{"status":"passed"},"match":{"location":"StepDefinition.Hooks.clearData()"}}],"type":"scenario","keyword":"Scenario Outline","steps":[{"result":{"status":"passed"},"line":14,"name":"User is on Net bank login page","match":{"location":"StepDefinition.login_Step.user_is_on_net_bank_login_page()"},"keyword":"Given "},{"result":{"status":"passed"},"line":15,"name":"User enter username \"DebitcardUser\" and password 100","match":{"arguments":[{"val":"\"DebitcardUser\"","offset":20},{"val":"100","offset":49}],"location":"StepDefinition.login_Step.user_enter_user_name_and_password(java.lang.String,java.lang.String)"},"keyword":"When "},{"result":{"status":"passed"},"line":16,"name":"User uccessfully navigate to the home page","match":{"location":"StepDefinition.login_Step.user_uccessfully_navigate_to_the_home_page()"},"keyword":"Then "}],"tags":[{"name":"@smoke"},{"name":"@Regration"},{"name":"@Netbank"}]},{"line":3,"name":"","description":"","type":"background","keyword":"Background","steps":[{"result":{"status":"passed"},"line":5,"name":"User enter launches browser from config file","match":{"location":"StepDefinition.login_Step.launchBrowser()"},"keyword":"When "},{"result":{"status":"passed"},"line":6,"name":"user get the URL","match":{"location":"StepDefinition.login_Step.getUrl()"},"keyword":"And "}]},{"start_timestamp":"2023-12-17T13:16:14.071Z","before":[{"result":{"status":"passed"},"match":{"location":"StepDefinition.Hooks.creditBanking()"}}],"line":26,"name":"Userregistration signup page","description":"","id":"login-page-hooks-feature;userregistration-signup-page","after":[{"result":{"status":"passed"},"match":{"location":"StepDefinition.Hooks.clearData()"}}],"type":"scenario","keyword":"Scenario","steps":[{"result":{"status":"passed"},"line":27,"name":"User is on registration page","match":{"location":"StepDefinition.login_Step.user_is_on_registration_page()"},"keyword":"Given "},{"result":{"status":"passed"},"line":28,"name":"User enter details in regisyration page","match":{"location":"StepDefinition.login_Step.user_enter_details_in_regisyration_page(java.util.List<java.lang.Object>)"},"rows":[{"cells":["anj"]},{"cells":["martha"]},{"cells":["man"]},{"cells":["anj@gmail.com"]},{"cells":["1.009"]},{"cells":["504502"]}],"keyword":"When "},{"result":{"status":"passed"},"line":36,"name":"User successfully registered","match":{"location":"StepDefinition.login_Step.user_successfully_registered()"},"keyword":"Then "}],"tags":[{"name":"@Unit"},{"name":"@Regration"},{"name":"@Creditbank"}]}],"name":"Login page hooks Feature","description":"","id":"login-page-hooks-feature","keyword":"Feature","uri":"file:src/test/java/feature/login2_hooks.feature","tags":[]}]